{
  "version": "v4.0.0-beta.1",
  "flags": {},
  "shapes": [
    {
      "label": "person",
      "score": null,
      "points": [
        [
          114.12374614197536,
          135.0998263888889
        ],
        [
          513.1544174382717,
          135.0998263888889
        ],
        [
          513.1544174382717,
          243.43315972222223
        ],
        [
          114.12374614197536,
          243.43315972222223
        ]
      ],
      "group_id": null,
      "description": "",
      "difficult": false,
      "shape_type": "rectangle",
      "flags": {},
      "attributes": {},
      "kie_linking": []
    },
    {
      "label": "right_shoulder",
      "score": null,
      "points": [
        [
          395.18807870370375,
          158.4963348765432
        ]
      ],
      "group_id": null,
      "description": "",
      "difficult": false,
      "shape_type": "point",
      "flags": {},
      "attributes": {},
      "kie_linking": []
    },
    {
      "label": "right_elbow",
      "score": null,
      "points": [
        [
          449.1763117283951,
          177.86603009259255
        ]
      ],
      "group_id": null,
      "description": "",
      "difficult": false,
      "shape_type": "point",
      "flags": {},
      "attributes": {},
      "kie_linking": []
    },
    {
      "label": "right_wrist",
      "score": null,
      "points": [
        [
          492.2583912037037,
          187.47251157407408
        ]
      ],
      "group_id": null,
      "description": "",
      "difficult": false,
      "shape_type": "point",
      "flags": {},
      "attributes": {},
      "kie_linking": []
    },
    {
      "label": "left_wrist",
      "score": null,
      "points": [
        [
          462.30806327160496,
          171.18441358024688
        ]
      ],
      "group_id": null,
      "description": "",
      "difficult": false,
      "shape_type": "point",
      "flags": {},
      "attributes": {},
      "kie_linking": []
    },
    {
      "label": "right_hip",
      "score": null,
      "points": [
        [
          316.043113425926,
          166.8393132716049
        ]
      ],
      "group_id": null,
      "description": "",
      "difficult": false,
      "shape_type": "point",
      "flags": {},
      "attributes": {},
      "kie_linking": []
    },
    {
      "label": "left_hip",
      "score": null,
      "points": [
        [
          303.11631944444446,
          145.87336033950618
        ]
      ],
      "group_id": null,
      "description": "",
      "difficult": false,
      "shape_type": "point",
      "flags": {},
      "attributes": {},
      "kie_linking": []
    },
    {
      "label": "left_knee",
      "score": null,
      "points": [
        [
          232.2227044753087,
          162.70158179012344
        ]
      ],
      "group_id": null,
      "description": null,
      "difficult": false,
      "shape_type": "point",
      "flags": {},
      "attributes": {},
      "kie_linking": []
    },
    {
      "label": "right_knee",
      "score": null,
      "points": [
        [
          243.66898148148152,
          189.0977044753086
        ]
      ],
      "group_id": null,
      "description": "",
      "difficult": false,
      "shape_type": "point",
      "flags": {},
      "attributes": {},
      "kie_linking": []
    },
    {
      "label": "right_ankle",
      "score": null,
      "points": [
        [
          160.52613811728398,
          204.09095293209873
        ]
      ],
      "group_id": null,
      "description": "",
      "difficult": false,
      "shape_type": "point",
      "flags": {},
      "attributes": {},
      "kie_linking": []
    },
    {
      "label": "left_ankle",
      "score": null,
      "points": [
        [
          143.48090277777783,
          169.2626350308642
        ]
      ],
      "group_id": null,
      "description": "",
      "difficult": false,
      "shape_type": "point",
      "flags": {},
      "attributes": {},
      "kie_linking": []
    }
  ],
  "imagePath": "frame_0094.jpg",
  "imageData": null,
  "imageHeight": 360,
  "imageWidth": 640,
  "description": ""
}