{
  "version": "v4.0.0-beta.1",
  "flags": {},
  "shapes": [
    {
      "label": "person",
      "score": null,
      "points": [
        [
          282.27816358024694,
          96.07108410493827
        ],
        [
          593.1071566358025,
          96.07108410493827
        ],
        [
          593.1071566358025,
          182.1436149691358
        ],
        [
          282.27816358024694,
          182.1436149691358
        ]
      ],
      "group_id": null,
      "description": "",
      "difficult": false,
      "shape_type": "rectangle",
      "flags": {},
      "attributes": {},
      "kie_linking": []
    },
    {
      "label": "right_shoulder",
      "score": null,
      "points": [
        [
          566.7062114197531,
          167.44936342592592
        ]
      ],
      "group_id": null,
      "description": "",
      "difficult": false,
      "shape_type": "point",
      "flags": {},
      "attributes": {},
      "kie_linking": []
    },
    {
      "label": "right_elbow",
      "score": null,
      "points": [
        [
          535.4103973765433,
          144.4362461419753
        ]
      ],
      "group_id": null,
      "description": "",
      "difficult": false,
      "shape_type": "point",
      "flags": {},
      "attributes": {},
      "kie_linking": []
    },
    {
      "label": "right_wrist",
      "score": null,
      "points": [
        [
          497.77295524691357,
          159.93586033950618
        ]
      ],
      "group_id": null,
      "description": "",
      "difficult": false,
      "shape_type": "point",
      "flags": {},
      "attributes": {},
      "kie_linking": []
    },
    {
      "label": "right_hip",
      "score": null,
      "points": [
        [
          465.54880401234567,
          146.2037037037037
        ]
      ],
      "group_id": null,
      "description": "",
      "difficult": false,
      "shape_type": "point",
      "flags": {},
      "attributes": {},
      "kie_linking": []
    },
    {
      "label": "left_hip",
      "score": null,
      "points": [
        [
          457.21064814814815,
          121.36284722222221
        ]
      ],
      "group_id": null,
      "description": "",
      "difficult": false,
      "shape_type": "point",
      "flags": {},
      "attributes": {},
      "kie_linking": []
    },
    {
      "label": "left_knee",
      "score": null,
      "points": [
        [
          393.94868827160496,
          124.41068672839508
        ]
      ],
      "group_id": null,
      "description": "",
      "difficult": false,
      "shape_type": "point",
      "flags": {},
      "attributes": {},
      "kie_linking": []
    },
    {
      "label": "right_knee",
      "score": null,
      "points": [
        [
          391.08169367283955,
          137.44598765432102
        ]
      ],
      "group_id": null,
      "description": "",
      "difficult": false,
      "shape_type": "point",
      "flags": {},
      "attributes": {},
      "kie_linking": []
    },
    {
      "label": "right_ankle",
      "score": null,
      "points": [
        [
          324.26552854938274,
          119.26263503086419
        ]
      ],
      "group_id": null,
      "description": "",
      "difficult": false,
      "shape_type": "point",
      "flags": {},
      "attributes": {},
      "kie_linking": []
    },
    {
      "label": "left_ankle",
      "score": null,
      "points": [
        [
          324.5862268518519,
          105.54253472222221
        ]
      ],
      "group_id": null,
      "description": "",
      "difficult": false,
      "shape_type": "point",
      "flags": {},
      "attributes": {},
      "kie_linking": []
    }
  ],
  "imagePath": "frame_0075.jpg",
  "imageData": null,
  "imageHeight": 360,
  "imageWidth": 640,
  "description": ""
}